markdown_pydantic/app.py
markdown_pydantic/extension.py
markdown_pydantic/files.py
markdown_pydantic/models/core.py
markdown_pydantic/processor.py
markdown_pydantic/py.typed
markdown_pydantic/templates.py
markdown_pydantic/types/simple.py
markdown_pydantic-0.2.0.dist-info/entry_points.txt
markdown_pydantic-0.2.0.dist-info/WHEEL
markdown_pydantic-0.2.0.dist-info/METADATA
markdown_pydantic-0.2.0.dist-info/RECORD
