Metadata-Version: 2.1
Name: markdown-pydantic
Version: 0.2.0
Summary: 
License: None
Author: Piotr Katolik
Author-email: katolus@ventress.org
Requires-Python: >=3.9,<4.0
Classifier: License :: Other/Proprietary License
Classifier: Programming Language :: Python :: 3
Classifier: Programming Language :: Python :: 3.10
Classifier: Programming Language :: Python :: 3.9
Requires-Dist: Markdown (>=3.3.7,<4.0.0)
Requires-Dist: PyYAML (>=6.0,<7.0)
Requires-Dist: pydantic (>=1.9.1,<2.0.0)
